Metadata-Version: 1.1
Name: mingpython
Version: 0.0.2
Summary: Automatically set package version from Git.
Home-page: https://gitee.com/minglie/mingpython
Author: minglie
Author-email: 934031452@qq.com
License: http://opensource.org/licenses/MIT
Platform: UNKNOWN
Classifier: Intended Audience :: Developers
Classifier: License :: OSI Approved :: MIT License
Classifier: Programming Language :: Python
